meteo_bz_dvdvnl/__init__.py
meteo_bz_dvdvnl/const.py
meteo_bz_dvdvnl/meteo_bz_client.py
meteo_bz_dvdvnl/meteo_bz_sensor.py
meteo_bz_dvdvnl/meteo_bz_station.py
meteo_bz_dvdvnl/reqiurements.txt
meteo_bz_dvdvnl-0.0.5.dist-info/METADATA
meteo_bz_dvdvnl-0.0.5.dist-info/WHEEL
meteo_bz_dvdvnl-0.0.5.dist-info/licenses/LICENSE
meteo_bz_dvdvnl-0.0.5.dist-info/RECORD
