Metadata-Version: 2.4
Name: meteo_bz_dvdvnl
Version: 0.0.5
Summary: Python client for the meteo API, provided by Provincia autonoma di Bolzano - Informatica Alto Adige SPA.
Project-URL: Homepage, https://github.com/dvdvnl/meteo_bz
Project-URL: Issues, https://github.com/dvdvnl/meteo_bz/issues
Author-email: david vnl <io@davole.com>
License-File: LICENSE
Classifier: License :: OSI Approved :: MIT License
Classifier: Operating System :: OS Independent
Classifier: Programming Language :: Python :: 3
Requires-Python: >=3.8
